[
    {
        "id": 1,
        "title": "Gravado",
        "image": "gravado.jpeg",
        "description": "Description 1",
        "link": "https://github.com/ColeWaggoner/07-08-GravadoP1"
    },
    {
        "id": 2,
        "title": "PandaCritic",
        "image": "pandacritic.jpeg",
        "description": "Description 2",
        "link": ""
    },
    {
        "id": 3,
        "title": "SubsTracker",
        "image": "substracker.jpeg",
        "description": "Description 3",
        "link": ""
    }
]